deprecation_alias/__init__.py
deprecation_alias/py.typed
deprecation_alias-0.3.3.dist-info/LICENSE
deprecation_alias-0.3.3.dist-info/METADATA
deprecation_alias-0.3.3.dist-info/WHEEL
deprecation_alias-0.3.3.dist-info/top_level.txt
deprecation_alias-0.3.3.dist-info/RECORD
