Metadata-Version: 2.1
Name: deprecation-alias
Version: 0.3.3
Summary: A wrapper around 'deprecation' providing support for deprecated aliases.
Home-page: https://github.com/domdfcoding/deprecation-alias
Author: Dominic Davis-Foster
Author-email: Dominic Davis-Foster <dominic@davis-foster.co.uk>
License: Apache License
Project-URL: Homepage, https://github.com/domdfcoding/deprecation-alias
Project-URL: Issue Tracker, https://github.com/domdfcoding/deprecation-alias/issues
Project-URL: Source Code, https://github.com/domdfcoding/deprecation-alias
Keywords: deprecation
Platform: Windows
Platform: macOS
Platform: Linux
Classifier: Development Status :: 4 - Beta
Classifier: Intended Audience :: Developers
Classifier: License :: OSI Approved :: Apache Software License
Classifier: Operating System :: OS Independent
Classifier: Programming Language :: Python
Classifier: Programming Language :: Python :: 3 :: Only
Classifier: Programming Language :: Python :: 3.6
Classifier: Programming Language :: Python :: 3.7
Classifier: Programming Language :: Python :: 3.8
Classifier: Programming Language :: Python :: 3.9
Classifier: Programming Language :: Python :: 3.10
Classifier: Programming Language :: Python :: 3.11
Classifier: Programming Language :: Python :: 3.12
Classifier: Programming Language :: Python :: Implementation :: CPython
Classifier: Programming Language :: Python :: Implementation :: PyPy
Classifier: Topic :: Software Development :: Libraries :: Python Modules
Classifier: Typing :: Typed
Requires-Python: >=3.6.1
License-File: LICENSE
Requires-Dist: deprecation >=2.1.0
Requires-Dist: packaging >=20.4
